torch_quant/__init__.py
torch_quant/amp_module.py
torch_quant/graph.py
torch_quant/module.py
torch_quant/observed_module.py
torch_quant/observer.py
torch_quant/quantizer.py
torch_quant/version.py
torch_quant-0.4.0.dist-info/METADATA
torch_quant-0.4.0.dist-info/WHEEL
torch_quant-0.4.0.dist-info/top_level.txt
torch_quant-0.4.0.dist-info/RECORD
